setup.py
pencil/__init__.py
pencil.egg-info/PKG-INFO
pencil.egg-info/SOURCES.txt
pencil.egg-info/dependency_links.txt
pencil.egg-info/not-zip-safe
pencil.egg-info/top_level.txt