Metadata-Version: 1.0
Name: pencil
Version: 0.6.2
Summary: Dumb but useful wrapper around Graphite URL API.
Home-page: https://github.com/20minutes/pencil
Author: Timothée Peignier
Author-email: tpeignier@20minutes.fr
License: UNKNOWN
Platform: UNKNOWN
Classifier: Intended Audience :: System Administrators
Classifier: Intended Audience :: Developers
Classifier: License :: OSI Approved :: MIT License
Classifier: Operating System :: OS Independent
Classifier: Programming Language :: Python
Classifier: Topic :: Utilities
